evercookie/__init__.py
evercookie/models.py
evercookie/urls.py
evercookie/views.py
evercookie/migrations/__init__.py
django_evercookie-0.1.0.dist-info/LICENSE
django_evercookie-0.1.0.dist-info/METADATA
django_evercookie-0.1.0.dist-info/WHEEL
django_evercookie-0.1.0.dist-info/top_level.txt
django_evercookie-0.1.0.dist-info/RECORD
